odoo9_addon_account_voucher_operating_unit-9.0.1.0.0.99.dev9-py2.7-nspkg.pth
odoo9_addon_account_voucher_operating_unit-9.0.1.0.0.99.dev9.dist-info/METADATA
odoo9_addon_account_voucher_operating_unit-9.0.1.0.0.99.dev9.dist-info/RECORD
odoo9_addon_account_voucher_operating_unit-9.0.1.0.0.99.dev9.dist-info/WHEEL
odoo9_addon_account_voucher_operating_unit-9.0.1.0.0.99.dev9.dist-info/namespace_packages.txt
odoo9_addon_account_voucher_operating_unit-9.0.1.0.0.99.dev9.dist-info/top_level.txt
odoo_addons/account_voucher_operating_unit/README.rst
odoo_addons/account_voucher_operating_unit/__init__.py
odoo_addons/account_voucher_operating_unit/__openerp__.py
odoo_addons/account_voucher_operating_unit/models/__init__.py
odoo_addons/account_voucher_operating_unit/models/account_voucher.py
odoo_addons/account_voucher_operating_unit/security/account_voucher_security.xml
odoo_addons/account_voucher_operating_unit/static/description/icon.png
odoo_addons/account_voucher_operating_unit/tests/__init__.py
odoo_addons/account_voucher_operating_unit/tests/test_account_voucher_operating_unit.py
odoo_addons/account_voucher_operating_unit/tests/test_receipt_operating_unit.py
odoo_addons/account_voucher_operating_unit/views/account_voucher_sales_purchase_view.xml
